liveramp_clean_room/__init__.py
liveramp_clean_room/config/api_config.toml
liveramp_clean_room/datahub/__init__.py
liveramp_clean_room/datahub/client.py
liveramp_clean_room/datahub/credentials.py
liveramp_clean_room-0.3.3.dist-info/METADATA
liveramp_clean_room-0.3.3.dist-info/WHEEL
liveramp_clean_room-0.3.3.dist-info/RECORD
