Metadata-Version: 2.1
Name: liveramp-clean-room
Version: 0.3.3
Summary: This is a python client that provides high level functions for interacting with liveramp's clean room.
Author: Datahub Eng
Author-email: datahub_ops@liveramp.com
Requires-Python: >=3.7.1,<4.0.0
Classifier: Programming Language :: Python :: 3
Classifier: Programming Language :: Python :: 3.8
Classifier: Programming Language :: Python :: 3.9
Classifier: Programming Language :: Python :: 3.10
Classifier: Programming Language :: Python :: 3.11
Requires-Dist: Jinja2 (>=3.1.2,<4.0.0)
Requires-Dist: backoff (>=2.2.1,<3.0.0)
Requires-Dist: cachetools (>=5.0.0,<6.0.0)
Requires-Dist: numpy (>=1.3,<2.0)
Requires-Dist: pandas (>=1.3,<2.0)
Requires-Dist: pyarrow (==9.0.0)
Requires-Dist: pytest (>=7.4.2,<8.0.0)
Requires-Dist: requests (>=2.31.0,<3.0.0)
Requires-Dist: sqlglot (>=18.1.0,<19.0.0)
Requires-Dist: toml (>=0.10.2,<0.11.0)
